{"stat.mineBlock.forestry.wood_pile":1,"stat.mineBlock.tconstruct.seared_tank":37,"stat.leaveGame":11,"stat.useItem.minecraft.soul_sand":19,"stat.pickup.bibliocraft.handdrill":2,"stat.pickup.tconstruct.edible":27,"stat.killEntity.Blaze":3,"stat.pickup.forestry.resources":179,"stat.mineBlock.minecraft.sandstone":9,"stat.pickup.tconstruct.faucet":2,"stat.useItem.minecraft.planks":1,"stat.pickup.minecraft.glowstone_dust":128,"stat.pickup.minecraft.porkchop":11,"stat.useItem.minecraft.water_bucket":25,"stat.mineBlock.minecraft.red_mushroom":5,"stat.pickup.minecraft.rotten_flesh":14,"stat.mineBlock.minecraft.nether_brick_fence":22,"stat.pickup.minecraft.sand":675,"stat.craftItem.minecraft.stone_axe":2,"stat.craftItem.tconstruct.casting":10,"stat.craftItem.minecraft.stone_sword":1,"stat.pickup.minecraft.brown_mushroom":2,"stat.mineBlock.minecraft.sand":655,"stat.useItem.tconstruct.slime_sapling":2,"stat.hopperInspected":12,"stat.useItem.yabba.item_barrel":28,"stat.useItem.minecraft.iron_pickaxe":254,"stat.pickup.tconstruct.slime_sapling":3,"stat.craftItem.minecraft.wooden_pickaxe":1,"stat.pickup.forestry.butterfly_ge":4,"stat.craftItem.minecraft.bed":2,"stat.mineBlock.forestry.logs.0":30,"stat.craftItem.forestry.smoker":1,"stat.furnaceInteraction":67,"stat.useItem.minecraft.nether_wart":39,"stat.craftItem.yabba.item_barrel":29,"stat.mineBlock.forestry.logs.3":39,"stat.mineBlock.forestry.logs.5":11,"stat.pickup.minecraft.nether_brick":651,"stat.entityKilledBy.WitherSkeleton":1,"stat.pickup.minecraft.beef":58,"stat.pickup.minecraft.furnace":1,"stat.useItem.minecraft.cooked_mutton":2,"stat.useItem.minecraft.redstone":7,"stat.craftItem.forestry.wrench":1,"stat.useItem.minecraft.trapdoor":3,"stat.useItem.tconstruct.stone_torch":489,"stat.useItem.minecraft.stone_stairs":179,"stat.mineBlock.tconstruct.ore":199,"stat.pickup.minecraft.stone_stairs":8,"stat.pickup.tconstruct.hammer":2,"stat.pickup.tconstruct.smeltery_io":2,"stat.useItem.minecraft.flint_and_steel":1,"stat.pickup.tconstruct.slime_dirt":48,"stat.pickup.forestry.bee_princess_ge":30,"stat.useItem.minecraft.hopper":4,"stat.mineBlock.minecraft.soul_sand":20,"stat.useItem.minecraft.dye":2,"stat.pickup.minecraft.lever":1,"stat.deaths":3,"stat.useItem.tconstruct.smeltery_io":5,"stat.pickup.minecraft.egg":29,"stat.playOneMinute":810814,"stat.pickup.tconstruct.rack":26,"stat.pickup.tconstruct.stone_torch":154,"stat.useItem.minecraft.nether_brick":29,"stat.craftItem.minecraft.iron_pickaxe":1,"stat.useItem.forestry.logs.0":7,"stat.mineBlock.minecraft.tallgrass":51,"stat.craftItem.minecraft.cooked_mutton":12,"stat.pickup.minecraft.netherrack":2191,"stat.pickup.tconstruct.seared":127,"stat.chestOpened":270,"stat.pickup.minecraft.pumpkin":4,"stat.useItem.minecraft.stone":36,"stat.pickup.tconstruct.casting":2,"stat.mineBlock.minecraft.netherrack":2430,"stat.pickup.minecraft.arrow":12,"stat.craftItem.minecraft.coal":36,"stat.mineBlock.tconstruct.faucet":2,"stat.pickup.tconstruct.excavator":1,"stat.fallOneCm":155837,"stat.crouchOneCm":4095,"stat.craftItem.tconstruct.toolforge":2,"stat.mineBlock.minecraft.chest":7,"stat.craftItem.minecraft.chest":46,"stat.craftItem.minecraft.iron_ingot":220,"stat.useItem.minecraft.nether_brick_fence":3,"stat.mineBlock.minecraft.lever":1,"stat.pickup.minecraft.red_mushroom":6,"stat.craftItem.minecraft.hopper":7,"stat.craftingTableInteraction":59,"stat.pickup.minecraft.nether_brick_fence":17,"stat.mineBlock.tconstruct.rack":26,"stat.craftItem.tconstruct.pattern":137,"stat.mineBlock.minecraft.log2":190,"stat.pickup.minecraft.feather":19,"stat.craftItem.minecraft.wooden_button":3,"stat.useItem.tconstruct.longsword":14,"stat.useItem.minecraft.furnace":1,"stat.useItem.minecraft.reeds":157,"stat.mineBlock.tconstruct.smeltery_io":2,"stat.craftItem.tconstruct.materials":152,"stat.pickup.minecraft.dye":64,"stat.pickup.minecraft.planks":1,"stat.useItem.forestry.wrench":12,"stat.pickup.minecraft.wheat_seeds":13,"stat.mineBlock.minecraft.gravel":498,"stat.useItem.minecraft.stone_pickaxe":1540,"stat.craftItem.tconstruct.seared_tank":15,"stat.useItem.minecraft.stone_sword":10,"stat.craftItem.minecraft.iron_leggings":2,"stat.mineBlock.yabba.item_barrel":10,"stat.mineBlock.minecraft.dirt":1923,"stat.useItem.ic2.scaffold":86,"stat.craftItem.minecraft.stone_stairs":180,"stat.pickup.minecraft.crafting_table":2,"stat.useItem.minecraft.cobblestone":750,"stat.pickup.minecraft.magma":34,"stat.craftItem.minecraft.crafting_table":11,"stat.mineBlock.minecraft.double_plant":1,"stat.pickup.tconstruct.pickaxe":1,"stat.killEntity.LavaSlime":2,"stat.pickup.minecraft.log":81,"stat.useItem.tconstruct.pickaxe":352,"stat.craftItem.minecraft.gold_ingot":8,"stat.pickup.minecraft.chicken":22,"stat.pickup.minecraft.sapling":60,"stat.pickup.forestry.fruits":149,"stat.pickup.minecraft.apple":3,"stat.craftItem.tconstruct.smeltery_controller":1,"stat.craftItem.minecraft.bucket":3,"stat.craftItem.minecraft.planks":696,"stat.mineBlock.tconstruct.toolforge":1,"stat.mineBlock.tconstruct.slime_grass":26,"stat.killEntity.WitherSkeleton":4,"stat.craftItem.tconstruct.stone_torch":432,"stat.pickup.minecraft.stone_sword":1,"stat.mineBlock.minecraft.log":80,"stat.craftItem.minecraft.cooked_chicken":4,"stat.mineBlock.forestry.sapling_ge":5,"stat.sneakTime":3304,"stat.pickup.minecraft.wool":16,"stat.pickup.ic2.scaffold":83,"stat.useItem.minecraft.wooden_axe":116,"stat.pickup.minecraft.chest":7,"stat.pickup.minecraft.bone":17,"stat.pickup.forestry.sapling":26,"stat.mineBlock.forestry.leaves":1,"stat.useItem.tconstruct.shuriken":15,"stat.useItem.minecraft.log2":26,"stat.mineBlock.minecraft.cobblestone":69,"stat.mineBlock.minecraft.pumpkin":4,"stat.pickup.minecraft.stone_pickaxe":1,"stat.pickup.minecraft.flint":42,"stat.craftItem.tconstruct.faucet":10,"stat.mineBlock.minecraft.brown_mushroom":1,"stat.craftItem.ic2.scaffold":120,"stat.useItem.bibliocraft.handdrill":14,"stat.swimOneCm":195768,"stat.climbOneCm":329,"stat.drop.minecraft.cobblestone":46,"stat.craftItem.minecraft.golden_chestplate":1,"stat.useItem.minecraft.obsidian":10,"stat.useItem.minecraft.dirt":342,"stat.useItem.minecraft.stone_slab2":196,"stat.craftItem.minecraft.furnace":3,"stat.useItem.tconstruct.excavator":2771,"stat.craftItem.forestry.planks.0":168,"stat.useItem.tconstruct.lumberaxe":256,"stat.mineBlock.ic2.scaffold":8,"stat.craftItem.minecraft.iron_boots":2,"stat.craftItem.minecraft.trapdoor":6,"stat.craftItem.forestry.ingot_bronze":4,"stat.craftItem.minecraft.stone_pickaxe":11,"stat.craftItem.minecraft.cooked_beef":40,"stat.mineBlock.minecraft.obsidian":71,"stat.mineBlock.minecraft.magma":40,"stat.pickup.minecraft.cobblestone":6822,"stat.mineBlock.minecraft.clay":152,"stat.useItem.minecraft.stone_shovel":288,"stat.flyOneCm":203108,"stat.craftItem.bibliocraft.framedchest":2,"stat.pickup.minecraft.soul_sand":20,"stat.pickup.minecraft.sandstone":9,"stat.useItem.forestry.planks.0":2,"stat.pickup.minecraft.nether_brick_stairs":5,"stat.craftItem.minecraft.wooden_slab":114,"stat.useItem.minecraft.cooked_beef":20,"stat.pickup.minecraft.cactus":12,"stat.craftItem.yabba.upgrade_blank":112,"stat.pickup.minecraft.redstone":544,"stat.mineBlock.minecraft.iron_ore":192,"stat.timeSinceDeath":248970,"stat.pickup.yabba.item_barrel":10,"stat.craftItem.forestry.wood_pile":1,"stat.pickup.minecraft.mutton":25,"stat.drop.forestry.scoop":1,"stat.craftItem.minecraft.iron_block":4,"stat.craftItem.tconstruct.seared":921,"stat.pickup.minecraft.nether_wart":111,"stat.pickup.tconstruct.soil":28,"stat.drop.minecraft.dirt":10,"stat.useItem.tconstruct.rack":42,"stat.pickup.minecraft.trapdoor":2,"stat.mineBlock.minecraft.coal_ore":502,"stat.mineBlock.minecraft.nether_brick":730,"stat.killEntity.Creeper":5,"stat.craftItem.tconstruct.soil":528,"stat.pickup.forestry.bee_combs":24,"stat.pickup.minecraft.string":5,"stat.pickup.tconstruct.smeltery_controller":1,"stat.craftItem.tconstruct.slime_boots":1,"stat.craftItem.minecraft.stone_slab2":3,"stat.craftItem.forestry.scoop":4,"stat.craftItem.tconstruct.stone_stick":131,"stat.craftItem.tconstruct.tooltables":13,"stat.killEntity.Squid":4,"stat.sprintOneCm":198718,"stat.craftItem.bibliocraft.handdrill":1,"stat.useItem.tconstruct.slime_dirt":9,"stat.craftItem.minecraft.stick":232,"stat.craftItem.minecraft.wooden_axe":1,"stat.craftItem.bibliocraft.label":2,"stat.mineBlock.minecraft.diamond_ore":3,"stat.useItem.tconstruct.casting":5,"stat.mineBlock.minecraft.crafting_table":2,"stat.pickup.forestry.logs.3":38,"stat.useItem.minecraft.diamond_pickaxe":150,"stat.pickup.forestry.logs.0":25,"stat.pickup.forestry.logs.5":11,"stat.useItem.tconstruct.seared_tank":33,"stat.mineBlock.minecraft.planks":1,"stat.drop":58,"stat.mineBlock.forestry.leaves.default.3":25,"stat.killEntity.Sheep":16,"stat.pickup.tconstruct.ore":195,"stat.useItem.tconstruct.seared":291,"stat.pickup.minecraft.slime_ball":9,"stat.craftItem.minecraft.diamond_pickaxe":1,"stat.killEntity.Zombie":12,"stat.mineBlock.forestry.leaves.default.0":3,"stat.craftItem.minecraft.dye":3,"stat.mineBlock.forestry.leaves.default.1":81,"stat.mineBlock.forestry.leaves.default.2":11,"stat.useItem.tconstruct.hammer":10906,"stat.craftItem.minecraft.clay":151,"stat.mineBlock.minecraft.gold_ore":36,"stat.diveOneCm":97999,"stat.drop.minecraft.diamond_pickaxe":1,"stat.pickup.tconstruct.tooltables":7,"stat.pickup.tconstruct.toolforge":1,"stat.pickup.minecraft.gravel":443,"stat.craftItem.minecraft.cooked_porkchop":2,"stat.killEntity.Slime":19,"stat.mineBlock.tconstruct.smeltery_controller":1,"stat.useItem.forestry.fruits":144,"stat.mineBlock.tconstruct.slime_leaves":2,"stat.useItem.minecraft.apple":2,"stat.mineBlock.minecraft.deadbush":1,"stat.pickup.minecraft.obsidian":60,"stat.pickup.tconstruct.sharpening_kit":33,"stat.mineBlock.tconstruct.slime_dirt":25,"stat.jump":5610,"stat.craftItem.tconstruct.rack":20,"stat.pickup.minecraft.coal":501,"stat.pickup.forestry.wood_pile":1,"stat.pickup.minecraft.iron_ingot":2,"stat.pickup.tconstruct.seared_tank":37,"stat.craftItem.minecraft.lever":1,"stat.useItem.minecraft.stone_axe":154,"stat.mineBlock.forestry.beehives":30,"stat.pickup.minecraft.gunpowder":4,"stat.pickup.minecraft.spider_eye":1,"stat.pickup.minecraft.dirt":1604,"stat.craftItem.minecraft.iron_helmet":2,"stat.useItem.minecraft.cooked_chicken":4,"stat.pickup.minecraft.iron_ore":191,"stat.pickup.tconstruct.slime_congealed":55,"stat.pickup.minecraft.gold_ore":36,"stat.craftItem.minecraft.flint_and_steel":2,"stat.mineBlock.minecraft.lapis_ore":11,"stat.mineBlock.tconstruct.tooltables":7,"stat.mineBlock.minecraft.leaves2":46,"stat.mineBlock.minecraft.stone_stairs":8,"stat.damageTaken":3846,"stat.pickup.minecraft.leather":26,"stat.craftItem.minecraft.iron_bars":16,"stat.mineBlock.minecraft.furnace":1,"stat.killEntity.tconstruct.blueslime":20,"stat.useItem.minecraft.wooden_pickaxe":60,"stat.pickup.minecraft.log2":189,"stat.useItem.forestry.scoop":33,"stat.pickup.minecraft.reeds":455,"stat.mineBlock.tconstruct.stone_torch":99,"stat.pickup.minecraft.bed":2,"stat.damageDealt":14539,"stat.craftItem.minecraft.glass":1,"stat.sleepInBed":15,"stat.mineBlock.minecraft.nether_brick_stairs":5,"stat.killEntity.Cow":29,"stat.killEntity.Pig":5,"stat.craftItem.minecraft.stone_shovel":3,"stat.craftItem.yabba.upgrade_iron_tier":3,"stat.walkOneCm":2944975,"stat.useItem.minecraft.chest":3,"stat.craftItem.tconstruct.smeltery_io":9,"stat.pickup.minecraft.stick":2,"stat.pickup.minecraft.diamond_pickaxe":1,"stat.pickup.minecraft.clay_ball":604,"stat.useItem.minecraft.lava_bucket":1,"stat.craftItem.forestry.ingot_tin":36,"stat.useItem.tconstruct.faucet":7,"stat.craftItem.forestry.ingot_copper":3,"stat.pickup.minecraft.stone":1137,"stat.craftItem.minecraft.iron_chestplate":1,"stat.useItem.minecraft.netherrack":93,"stat.killEntity.Skeleton":10,"stat.pickup.forestry.bee_drone_ge":25,"stat.pickup.forestry.apatite":400,"stat.mineBlock.minecraft.cactus":10,"stat.pickup.forestry.scoop":1,"stat.killEntity.Chicken":22,"stat.killEntity.Spider":6,"stat.mineBlock.minecraft.quartz_ore":92,"stat.mineBlock.forestry.resources":273,"stat.mineBlock.minecraft.glowstone":46,"stat.mobKills":157,"stat.pickup.minecraft.quartz":92,"stat.pickup.minecraft.diamond":3,"stat.mineBlock.minecraft.leaves":54,"stat.mineBlock.tconstruct.seared":127,"stat.mineBlock.minecraft.redstone_ore":122,"stat.mineBlock.tconstruct.casting":2,"stat.useItem.tconstruct.battlesign":5,"stat.craftItem.forestry.can":12,"stat.mineBlock.minecraft.stone":8000,"stat.useItem.tconstruct.hatchet":11,"stat.useItem.minecraft.sandstone":8}